fastybird_redisdb_exchange_plugin/__init__.py
fastybird_redisdb_exchange_plugin/bootstrap.py
fastybird_redisdb_exchange_plugin/client.py
fastybird_redisdb_exchange_plugin/events.py
fastybird_redisdb_exchange_plugin/exceptions.py
fastybird_redisdb_exchange_plugin/logger.py
fastybird_redisdb_exchange_plugin/publisher.py
fastybird_redisdb_exchange_plugin/py.typed
tests/__init__.py
tests/pytests/__init__.py
tests/pytests/tests.py
fastybird_redisdb_exchange_plugin-0.59.0.dist-info/LICENSE.md
fastybird_redisdb_exchange_plugin-0.59.0.dist-info/METADATA
fastybird_redisdb_exchange_plugin-0.59.0.dist-info/WHEEL
fastybird_redisdb_exchange_plugin-0.59.0.dist-info/top_level.txt
fastybird_redisdb_exchange_plugin-0.59.0.dist-info/RECORD
